bunnybase/__init__.py
bunnybase/data.py
bunnybase/datalist.py
bunnybase/hub.py
bunnybase/save.py
bunnybase/utils.py
bunnybase-0.1.11.dist-info/LICENSE
bunnybase-0.1.11.dist-info/METADATA
bunnybase-0.1.11.dist-info/WHEEL
bunnybase-0.1.11.dist-info/RECORD
