Metadata-Version: 2.1
Name: bunnybase
Version: 0.1.11
Summary: Datamanaging system
Home-page: https://github.com/trollmii/bunnybase
Author: trollmii
Author-email: trollmii@outlook.de
Requires-Python: >=3.10,<4.0
Classifier: Programming Language :: Python :: 3
Classifier: Programming Language :: Python :: 3.10
Classifier: Programming Language :: Python :: 3.11
Classifier: Programming Language :: Python :: 3.12
Classifier: Programming Language :: Python :: 3.13
Requires-Dist: numpy (>=2.1.0,<3.0.0)
Requires-Dist: pandas (>=2.1.0,<3.0.0)
Requires-Dist: pillow (>=11.1.0,<12.0.0)
Requires-Dist: pyarrow (>=19.0.1,<20.0.0)
Project-URL: Repository, https://github.com/trollmii/bunnybase
